gdriveaudio/__init__.py
gdriveaudio/gdriveaudio.py
gdriveaudio-0.1.15.dist-info/LICENSE
gdriveaudio-0.1.15.dist-info/METADATA
gdriveaudio-0.1.15.dist-info/WHEEL
gdriveaudio-0.1.15.dist-info/entry_points.txt
gdriveaudio-0.1.15.dist-info/top_level.txt
gdriveaudio-0.1.15.dist-info/RECORD
